pyhello/__init__.py
pyhello/hello.py
pyhello-0.0.1.dist-info/LICENSE.md
pyhello-0.0.1.dist-info/METADATA
pyhello-0.0.1.dist-info/WHEEL
pyhello-0.0.1.dist-info/top_level.txt
pyhello-0.0.1.dist-info/RECORD
